AUTHORS.rst
CONTRIBUTING.rst
HISTORY.rst
LICENSE
MANIFEST.in
README.rst
pyproject.toml
requirements.txt
requirements_dev.txt
setup.cfg
setup.py
docs/Makefile
docs/authors.rst
docs/conf.py
docs/contributing.rst
docs/history.rst
docs/index.rst
docs/installation.rst
docs/make.bat
docs/readme.rst
docs/usage.rst
pyscard_json_rpc/__init__.py
pyscard_json_rpc/app.py
pyscard_json_rpc/cli.py
pyscard_json_rpc/connections.py
pyscard_json_rpc/json_rpc.py
pyscard_json_rpc/methods.py
pyscard_json_rpc/observers.py
pyscard_json_rpc.egg-info/PKG-INFO
pyscard_json_rpc.egg-info/SOURCES.txt
pyscard_json_rpc.egg-info/dependency_links.txt
pyscard_json_rpc.egg-info/entry_points.txt
pyscard_json_rpc.egg-info/not-zip-safe
pyscard_json_rpc.egg-info/requires.txt
pyscard_json_rpc.egg-info/top_level.txt
tests/__init__.py
tests/test_pyscard_json_rpc.py