Metadata-Version: 1.2
Name: pyscard-json-rpc
Version: 0.2.0
Summary: JSON RPC bindings for pyscard.
Home-page: https://github.com/namespace-ee/pyscard-json-rpc
Author: Namespace OÜ
Author-email: info@namespace.ee
License: MIT license
Keywords: pyscard-json-rpc
Platform: UNKNOWN
Classifier: Development Status :: 2 - Pre-Alpha
Classifier: Intended Audience :: Developers
Classifier: License :: OSI Approved :: MIT License
Classifier: Natural Language :: English
Classifier: Programming Language :: Python :: 3
Classifier: Programming Language :: Python :: 3.6
Classifier: Programming Language :: Python :: 3.7
Classifier: Programming Language :: Python :: 3.8
Requires-Python: >=3.6
